eaterate/__init__.py
eaterate/core.py
eaterate/option.py
eaterate/range.py
eaterate/repeating.py
eaterate/result.py
eaterate-0.2.0.dist-info/WHEEL
eaterate-0.2.0.dist-info/METADATA
eaterate-0.2.0.dist-info/RECORD
