Metadata-Version: 2.4
Name: eaterate
Version: 0.2.0
Summary: Modern Python iterators.
Keywords: iterator
Author-email: AWeirdDev <awdjared@gmail.com>
Requires-Python: >=3.10
License-Expression: MIT
Classifier: Programming Language :: Python :: 3
Classifier: Operating System :: OS Independent
